rest_framework_jwt/__init__.py
rest_framework_jwt/authentication.py
rest_framework_jwt/compat.py
rest_framework_jwt/models.py
rest_framework_jwt/permissions.py
rest_framework_jwt/serializers.py
rest_framework_jwt/settings.py
rest_framework_jwt/utils.py
rest_framework_jwt/views.py
rest_framework_jwt/blacklist/__init__.py
rest_framework_jwt/blacklist/admin.py
rest_framework_jwt/blacklist/apps.py
rest_framework_jwt/blacklist/exceptions.py
rest_framework_jwt/blacklist/models.py
rest_framework_jwt/blacklist/permissions.py
rest_framework_jwt/blacklist/serializers.py
rest_framework_jwt/blacklist/settings.py
rest_framework_jwt/blacklist/signals.py
rest_framework_jwt/blacklist/views.py
rest_framework_jwt/blacklist/management/__init__.py
rest_framework_jwt/blacklist/management/commands/__init__.py
rest_framework_jwt/blacklist/management/commands/delete_stale_tokens.py
rest_framework_jwt/blacklist/migrations/0001_initial.py
rest_framework_jwt/blacklist/migrations/0002_add_token_id.py
rest_framework_jwt/blacklist/migrations/__init__.py
rest_framework_jwt/management/__init__.py
rest_framework_jwt/management/commands/__init__.py
rest_framework_jwt/management/commands/obtain_token.py
drf_jwt-1.19.2.dist-info/LICENSE
drf_jwt-1.19.2.dist-info/METADATA
drf_jwt-1.19.2.dist-info/WHEEL
drf_jwt-1.19.2.dist-info/top_level.txt
drf_jwt-1.19.2.dist-info/RECORD
