Metadata-Version: 2.1
Name: drf-jwt
Version: 1.19.2
Summary: JSON Web Token based authentication for Django REST framework
Home-page: https://github.com/Styria-Digital/django-rest-framework-jwt
Author: Styria Digital
Author-email: digital-development@styria.hr
License: MIT
Keywords: Styria CMS,JSON API
Platform: POSIX
Platform: Microsoft
Platform: MacOS
Classifier: Development Status :: 5 - Production/Stable
Classifier: Environment :: Web Environment
Classifier: Framework :: Django
Classifier: Intended Audience :: Developers
Classifier: License :: OSI Approved :: MIT License
Classifier: Operating System :: OS Independent
Classifier: Programming Language :: Python
Classifier: Programming Language :: Python :: 2
Classifier: Programming Language :: Python :: 2.7
Classifier: Programming Language :: Python :: 3
Classifier: Programming Language :: Python :: 3.5
Classifier: Programming Language :: Python :: 3.6
Classifier: Programming Language :: Python :: 3.7
Classifier: Topic :: Internet :: WWW/HTTP
Requires-Python: !=3.0.*,!=3.1.*,!=3.2.*,!=3.3.*,!=3.4.*,>=2.7
Provides-Extra: dev
Provides-Extra: lint
Provides-Extra: test
Provides-Extra: docs
